CONTRIBUTING.md
LICENSE
MANIFEST.in
README.md
setup.cfg
setup.py
microcosm_sagemaker/__init__.py
microcosm_sagemaker/app_hooks.py
microcosm_sagemaker/artifact.py
microcosm_sagemaker/bundle.py
microcosm_sagemaker/bundle_orchestrator.py
microcosm_sagemaker/bundle_traversal.py
microcosm_sagemaker/constants.py
microcosm_sagemaker/decorators.py
microcosm_sagemaker/dependency_traverser.py
microcosm_sagemaker/distributed_cluster.py
microcosm_sagemaker/evaluation.py
microcosm_sagemaker/exceptions.py
microcosm_sagemaker/factories.py
microcosm_sagemaker/input_data.py
microcosm_sagemaker/loaders.py
microcosm_sagemaker/pickling_bundle.py
microcosm_sagemaker/profiling.py
microcosm_sagemaker/random.py
microcosm_sagemaker/s3.py
microcosm_sagemaker/training_initializer_registry.py
microcosm_sagemaker.egg-info/PKG-INFO
microcosm_sagemaker.egg-info/SOURCES.txt
microcosm_sagemaker.egg-info/dependency_links.txt
microcosm_sagemaker.egg-info/entry_points.txt
microcosm_sagemaker.egg-info/not-zip-safe
microcosm_sagemaker.egg-info/requires.txt
microcosm_sagemaker.egg-info/top_level.txt
microcosm_sagemaker/commands/__init__.py
microcosm_sagemaker/commands/config.py
microcosm_sagemaker/commands/evaluate.py
microcosm_sagemaker/commands/options.py
microcosm_sagemaker/commands/runserver.py
microcosm_sagemaker/commands/train.py
microcosm_sagemaker/commands/train_one_bundle.py
microcosm_sagemaker/conventions/__init__.py
microcosm_sagemaker/conventions/invocations.py
microcosm_sagemaker/frameworks/__init__.py
microcosm_sagemaker/frameworks/tensorflow/__init__.py
microcosm_sagemaker/frameworks/torch/__init__.py
microcosm_sagemaker/metrics/__init__.py
microcosm_sagemaker/metrics/experiment_metrics.py
microcosm_sagemaker/metrics/wandb/__init__.py
microcosm_sagemaker/metrics/wandb/store.py
microcosm_sagemaker/metrics/wandb/wandb_config.py
microcosm_sagemaker/testing/__init__.py
microcosm_sagemaker/testing/bundle.py
microcosm_sagemaker/testing/bundle_prediction_check.py
microcosm_sagemaker/testing/bytes_extractor.py
microcosm_sagemaker/testing/cli_test_case.py
microcosm_sagemaker/testing/directory_comparison.py
microcosm_sagemaker/testing/evaluate.py
microcosm_sagemaker/testing/evaluation.py
microcosm_sagemaker/testing/invocations.py
microcosm_sagemaker/testing/pickle_comparison.py
