Metadata-Version: 2.1
Name: microcosm-sagemaker
Version: 2023.8.3534
Summary: Opinionated machine learning organization and configuration
Home-page: https://github.com/globality-corp/microcosm-sagemaker
Author: Globality Engineering
Author-email: engineering@globality.com
Keywords: microcosm
Requires-Python: >=3.6
Provides-Extra: torch
Provides-Extra: tensorflow
Provides-Extra: test
Provides-Extra: lint
Provides-Extra: profiling
Provides-Extra: wandb
License-File: LICENSE
